ColabTurtleClass/Turtle.py
ColabTurtleClass/__init__.py
ColabTurtleClass-0.3.3.dist-info/LICENSE
ColabTurtleClass-0.3.3.dist-info/METADATA
ColabTurtleClass-0.3.3.dist-info/WHEEL
ColabTurtleClass-0.3.3.dist-info/top_level.txt
ColabTurtleClass-0.3.3.dist-info/RECORD
