Metadata-Version: 2.1
Name: ColabTurtleClass
Version: 0.3.3
Summary: Class Implementation of ColabTurtle
Home-page: https://github.com/abstrqt/ColabTurtleClass
Author: Kevin Shen
Author-email: UNKNOWN
License: MIT
Platform: UNKNOWN
Requires-Dist: IPython
